ffxiv_stats/__init__.py
ffxiv_stats/jobs.py
ffxiv_stats/modifiers.py
ffxiv_stats/moments.py
ffxiv_stats/rate.py
ffxiv_stats-0.6.0.dist-info/LICENSE
ffxiv_stats-0.6.0.dist-info/METADATA
ffxiv_stats-0.6.0.dist-info/WHEEL
ffxiv_stats-0.6.0.dist-info/RECORD
