Metadata-Version: 2.3
Name: ffxiv_stats
Version: 0.6.0
Summary: A stats analysis tool for FFXIV.
License: Apache-2.0
Author: Acerola Paracletus
Author-email: ffxivacerola@gmail.com
Requires-Python: >=3.9
Classifier: License :: OSI Approved :: Apache Software License
Classifier: Programming Language :: Python :: 3
Classifier: Programming Language :: Python :: 3.9
Classifier: Programming Language :: Python :: 3.10
Classifier: Programming Language :: Python :: 3.11
Classifier: Programming Language :: Python :: 3.12
Classifier: Programming Language :: Python :: 3.13
Requires-Dist: matplotlib (>=3.4.2)
Requires-Dist: numpy (>=1.20.2)
Requires-Dist: pandas (>=2.0.0)
Requires-Dist: scipy (>=1.6.3)
Project-URL: Home, https://github.com/ffxiv-acerola/ffxiv_stats
